midasflow/VERSION
midasflow/__init__.py
midasflow/_midasflow.py
midasflow-0.1.4.post5.dist-info/licenses/LICENSE
midasflow-0.1.4.post5.dist-info/METADATA
midasflow-0.1.4.post5.dist-info/WHEEL
midasflow-0.1.4.post5.dist-info/entry_points.txt
midasflow-0.1.4.post5.dist-info/top_level.txt
midasflow-0.1.4.post5.dist-info/RECORD
