Metadata-Version: 2.4
Name: midasflow
Version: 0.1.4.post5
Summary: MIDASFlow is the Python package for the Memory-Efficient I/O-Improved Drainage Analysis System (MIDAS).
Home-page: https://github.com/HuidaeCho/midasflow
Author: Huidae Cho
Author-email: grass4u@gmail.com
License: GPLv3+
Classifier: Programming Language :: Python :: 3
Classifier: License :: OSI Approved :: GNU General Public License v3 or later (GPLv3+)
Classifier: Operating System :: OS Independent
Requires-Python: >=3
License-File: LICENSE
Dynamic: author
Dynamic: author-email
Dynamic: classifier
Dynamic: description
Dynamic: description-content-type
Dynamic: home-page
Dynamic: license
Dynamic: license-file
Dynamic: requires-python
Dynamic: summary
